twitter_scraper/__init__.py
twitter_scraper/modules/__init__.py
twitter_scraper/modules/profile.py
twitter_scraper/modules/trends.py
twitter_scraper/modules/tweets.py
twitter_scraper-0.4.4.dist-info/LICENSE
twitter_scraper-0.4.4.dist-info/METADATA
twitter_scraper-0.4.4.dist-info/WHEEL
twitter_scraper-0.4.4.dist-info/top_level.txt
twitter_scraper-0.4.4.dist-info/RECORD
