Metadata-Version: 2.1
Name: twitter-scraper
Version: 0.4.4
Summary: Scrape the Twitter Frontend API without authentication.
Home-page: https://github.com/bisguzar/twitter-scraper
Author: Bugra Isguzar
Author-email: ben@bisguzar.com
License: MIT
Platform: UNKNOWN
Classifier: License :: OSI Approved :: MIT License
Classifier: Programming Language :: Python
Classifier: Programming Language :: Python :: 3.6
Classifier: Programming Language :: Python :: Implementation :: CPython
Classifier: Programming Language :: Python :: Implementation :: PyPy
